{"assets/icons/blood_pressure.svg":["assets/icons/blood_pressure.svg"],"assets/icons/hemoglobin.svg":["assets/icons/hemoglobin.svg"],"assets/icons/sugar.svg":["assets/icons/sugar.svg"],"assets/images/hero_bg.jpg":["assets/images/hero_bg.jpg"],"assets/images/hero_bg.png":["assets/images/hero_bg.png"],"assets/images/logo.png":["assets/images/logo.png"],"assets/images/rppg.png":["assets/images/rppg.png"],"assets/images/technology_demo.jpg":["assets/images/technology_demo.jpg"],"assets/images/user1.jpg":["assets/images/user1.jpg"],"assets/images/user2.jpg":["assets/images/user2.jpg"],"assets/images/user3.jpg":["assets/images/user3.jpg"],"assets/images/user4.jpg":["assets/images/user4.jpg"],"assets/images/user5.jpg":["assets/images/user5.jpg"],"assets/images/website_bg.png":["assets/images/website_bg.png"],"assets/images/workflow_demo.gif":["assets/images/workflow_demo.gif"],"packages/cupertino_icons/assets/CupertinoIcons.ttf":["packages/cupertino_icons/assets/CupertinoIcons.ttf"]}